[{"BatV":3.356,"TempC1":"23.40","Work_mode":"IIC","device_id":"west_reservoir_sensor","raw":"DRwA6gDwAP////8=","time":"2020-11-23T20:03:36.490230263Z"},{"BatV":3.356,"TempC1":"23.60","Work_mode":"IIC","device_id":"west_reservoir_sensor","raw":"DRwA7ADxAP////8=","time":"2020-11-23T20:18:36.207117428Z"},{"BatV":3.356,"TempC1":"23.80","Work_mode":"IIC","device_id":"west_reservoir_sensor","raw":"DRwA7gECAP////8=","time":"2020-11-23T20:33:36.432902527Z"},{"BatV":3.358,"TempC1":"23.90","Work_mode":"IIC","device_id":"west_reservoir_sensor","raw":"DR4A7wEFAP////8=","time":"2020-11-23T20:48:36.142356485Z"}]
