[{"BatV":3.347,"TempC1":"21.30","Work_mode":"IIC","device_id":"west_reservoir_sensor","raw":"DRMA1QEJAP////8=","time":"2020-11-10T22:19:05.865107303Z"},{"BatV":3.349,"TempC1":"21.30","Work_mode":"IIC","device_id":"west_reservoir_sensor","raw":"DRUA1QEKAP////8=","time":"2020-11-10T22:34:05.844229086Z"},{"BatV":3.349,"TempC1":"21.30","Work_mode":"IIC","device_id":"west_reservoir_sensor","raw":"DRUA1QD7AP////8=","time":"2020-11-10T22:49:05.814631231Z"},{"BatV":3.349,"TempC1":"21.10","Work_mode":"IIC","device_id":"west_reservoir_sensor","raw":"DRUA0wD2AP////8=","time":"2020-11-10T23:04:05.797341875Z"}]
