[{"BatV":3.266,"TempC1":"6.30","Work_mode":"IIC","device_id":"west_reservoir_sensor","raw":"DMIAPwJwgP////8=","time":"2020-10-09T05:58:08.146694438Z"},{"BatV":3.255,"TempC1":"6.30","Work_mode":"IIC","device_id":"west_reservoir_sensor","raw":"DLcAPwJigP////8=","time":"2020-10-09T06:13:08.134028403Z"},{"BatV":3.287,"TempC1":"6.30","Work_mode":"IIC","device_id":"west_reservoir_sensor","raw":"DNcAPwJqgP////8=","time":"2020-10-09T06:28:08.118397222Z"},{"BatV":3.264,"TempC1":"6.30","Work_mode":"IIC","device_id":"west_reservoir_sensor","raw":"DMAAPwJwgP////8=","time":"2020-10-09T06:43:08.12178406Z"}]
